Firmware/sim/ad9361_lvds_1r1t/rtl/nyquist_ad9361_lvds_1r1t_demo.sv
// SPDX-License-Identifier: MIT
//
// Protocol-level AD9361 1R1T DDR LVDS interface demonstration.
//
// IMPORTANT: This module is intentionally simulator-portable. It models both
// clock edges in behavioral SystemVerilog so that the AD9361 wire protocol can
// be demonstrated with Icarus Verilog. It is not the production Artix-7 PHY.
// The production design must instantiate UHD cat_io_lvds_dual_mode, which uses
// Xilinx 7-series ISERDESE2/OSERDESE2/IDELAYE2 primitives.

`timescale 1ns/1ps

module nyquist_ad9361_lvds_1r1t_demo (
    input  logic        rst,

    // AD9361 -> FPGA receive interface
    input  logic        rx_clk_p,
    input  logic        rx_clk_n,
    input  logic        rx_frame_p,
    input  logic        rx_frame_n,
    input  logic [5:0]  rx_d_p,
    input  logic [5:0]  rx_d_n,

    // Reconstructed FPGA receive sample
    output logic        rx_sample_valid,
    output logic [11:0] rx_i,
    output logic [11:0] rx_q,
    output logic [31:0] rx_packed,

    // FPGA transmit sample
    input  logic        tx_sample_valid,
    input  logic [11:0] tx_i,
    input  logic [11:0] tx_q,

    // FPGA -> AD9361 transmit interface
    output logic        tx_clk_p,
    output logic        tx_clk_n,
    output logic        tx_frame_p,
    output logic        tx_frame_n,
    output logic [5:0]  tx_d_p,
    output logic [5:0]  tx_d_n,

    // Demonstration/status counters
    output logic [31:0] rx_sample_count,
    output logic [31:0] tx_sample_count,
    output logic [31:0] rx_frame_error_count,
    output logic [31:0] rx_diff_error_count
);

    logic [1:0] rx_phase;
    logic [1:0] tx_phase;
    logic [11:0] rx_i_work;
    logic [11:0] rx_q_work;
    logic [11:0] tx_i_latched;
    logic [11:0] tx_q_latched;
    logic expected_frame;

    assign rx_packed = {rx_i, 4'b0000, rx_q, 4'b0000};
    assign tx_clk_p  = rx_clk_p;
    assign tx_clk_n  = rx_clk_n;
    assign tx_frame_n = ~tx_frame_p;
    assign tx_d_n     = ~tx_d_p;

    // The AD9361 1R1T LVDS sequence is one six-bit transfer per clock edge:
    //   phase 0: I[11:6], FRAME=1
    //   phase 1: Q[11:6], FRAME=1
    //   phase 2: I[5:0],  FRAME=0
    //   phase 3: Q[5:0],  FRAME=0
    // This behavioral block observes both clock edges for portable simulation.
    always @(posedge rx_clk_p or negedge rx_clk_p or posedge rst) begin
        if (rst) begin
            rx_phase             = 2'd0;
            rx_i_work            = 12'd0;
            rx_q_work            = 12'd0;
            rx_i                 = 12'd0;
            rx_q                 = 12'd0;
            rx_sample_valid      = 1'b0;
            rx_sample_count      = 32'd0;
            rx_frame_error_count = 32'd0;
            rx_diff_error_count  = 32'd0;
        end else begin
            rx_sample_valid = 1'b0;
            expected_frame = (rx_phase < 2);

            if ((rx_clk_n !== ~rx_clk_p) ||
                (rx_frame_n !== ~rx_frame_p) ||
                (rx_d_n !== ~rx_d_p)) begin
                rx_diff_error_count = rx_diff_error_count + 1'b1;
            end

            if (rx_frame_p !== expected_frame) begin
                rx_frame_error_count = rx_frame_error_count + 1'b1;
            end

            case (rx_phase)
                2'd0: rx_i_work[11:6] = rx_d_p;
                2'd1: rx_q_work[11:6] = rx_d_p;
                2'd2: rx_i_work[5:0]  = rx_d_p;
                2'd3: begin
                    rx_q_work[5:0] = rx_d_p;
                    rx_i = rx_i_work;
                    rx_q = rx_q_work;
                    rx_sample_valid = 1'b1;
                    rx_sample_count = rx_sample_count + 1'b1;
                end
            endcase

            rx_phase = rx_phase + 1'b1;
        end
    end

    // Behavioral DDR transmitter. In hardware this function is implemented
    // with OSERDESE2/OBUFDS and source-synchronous forwarded-clock resources.
    always @(posedge rx_clk_p or negedge rx_clk_p or posedge rst) begin
        if (rst) begin
            tx_phase        = 2'd0;
            tx_i_latched    = 12'd0;
            tx_q_latched    = 12'd0;
            tx_frame_p      = 1'b0;
            tx_d_p          = 6'd0;
            tx_sample_count = 32'd0;
        end else begin
            if ((tx_phase == 2'd0) && tx_sample_valid) begin
                tx_i_latched = tx_i;
                tx_q_latched = tx_q;
            end

            case (tx_phase)
                2'd0: begin
                    tx_frame_p = 1'b1;
                    tx_d_p = tx_sample_valid ? tx_i[11:6] : 6'd0;
                end
                2'd1: begin
                    tx_frame_p = 1'b1;
                    tx_d_p = tx_q_latched[11:6];
                end
                2'd2: begin
                    tx_frame_p = 1'b0;
                    tx_d_p = tx_i_latched[5:0];
                end
                2'd3: begin
                    tx_frame_p = 1'b0;
                    tx_d_p = tx_q_latched[5:0];
                    if (tx_sample_valid)
                        tx_sample_count = tx_sample_count + 1'b1;
                end
            endcase

            tx_phase = tx_phase + 1'b1;
        end
    end

endmodule

Firmware/sim/ad9361_lvds_1r1t/tb/tb_nyquist_ad9361_lvds_1r1t.sv
// SPDX-License-Identifier: MIT

`timescale 1ns/1ps

module tb_nyquist_ad9361_lvds_1r1t;

    logic rst = 1'b0;

    logic       rx_clk_p = 1'b0;
    logic       rx_clk_n;
    logic       rx_frame_p = 1'b0;
    logic       rx_frame_n;
    logic [5:0] rx_d_p = 6'd0;
    logic [5:0] rx_d_n;

    logic        rx_sample_valid;
    logic [11:0] rx_i;
    logic [11:0] rx_q;
    logic [31:0] rx_packed;

    logic        tx_sample_valid = 1'b0;
    logic [11:0] tx_i = 12'd0;
    logic [11:0] tx_q = 12'd0;

    logic       tx_clk_p;
    logic       tx_clk_n;
    logic       tx_frame_p;
    logic       tx_frame_n;
    logic [5:0] tx_d_p;
    logic [5:0] tx_d_n;

    logic [31:0] rx_sample_count;
    logic [31:0] tx_sample_count;
    logic [31:0] rx_frame_error_count;
    logic [31:0] rx_diff_error_count;

    logic [1:0]  tx_check_phase = 2'd0;
    logic [11:0] tx_check_i = 12'd0;
    logic [11:0] tx_check_q = 12'd0;
    logic [11:0] expected_tx_i = 12'd0;
    logic [11:0] expected_tx_q = 12'd0;

    integer sample_index;
    integer errors = 0;
    integer checked_rx_samples = 0;
    integer checked_tx_samples = 0;
    integer inject_frame_error;
    reg [8*256-1:0] vcd_file;

    assign rx_clk_n   = ~rx_clk_p;
    assign rx_frame_n = ~rx_frame_p;
    assign rx_d_n     = ~rx_d_p;

    nyquist_ad9361_lvds_1r1t_demo dut (
        .rst,
        .rx_clk_p,
        .rx_clk_n,
        .rx_frame_p,
        .rx_frame_n,
        .rx_d_p,
        .rx_d_n,
        .rx_sample_valid,
        .rx_i,
        .rx_q,
        .rx_packed,
        .tx_sample_valid,
        .tx_i,
        .tx_q,
        .tx_clk_p,
        .tx_clk_n,
        .tx_frame_p,
        .tx_frame_n,
        .tx_d_p,
        .tx_d_n,
        .rx_sample_count,
        .tx_sample_count,
        .rx_frame_error_count,
        .rx_diff_error_count
    );

    task automatic check_tx_edge;
        logic expected_frame;
        begin
            expected_frame = (tx_check_phase < 2);

            if ((tx_clk_n !== ~tx_clk_p) ||
                (tx_frame_n !== ~tx_frame_p) ||
                (tx_d_n !== ~tx_d_p)) begin
                $display("ERROR TX differential complement failure at t=%0t", $time);
                errors = errors + 1;
            end

            if (tx_frame_p !== expected_frame) begin
                $display("ERROR TX frame phase=%0d expected=%0b got=%0b", tx_check_phase,
                    expected_frame, tx_frame_p);
                errors = errors + 1;
            end

            case (tx_check_phase)
                2'd0: tx_check_i[11:6] = tx_d_p;
                2'd1: tx_check_q[11:6] = tx_d_p;
                2'd2: tx_check_i[5:0]  = tx_d_p;
                2'd3: begin
                    tx_check_q[5:0] = tx_d_p;
                    if ((tx_check_i !== expected_tx_i) ||
                        (tx_check_q !== expected_tx_q)) begin
                        $display("ERROR TX sample expected I=%03h Q=%03h got I=%03h Q=%03h",
                            expected_tx_i, expected_tx_q, tx_check_i, tx_check_q);
                        errors = errors + 1;
                    end else begin
                        checked_tx_samples = checked_tx_samples + 1;
                    end
                end
            endcase

            tx_check_phase = tx_check_phase + 1'b1;
        end
    endtask

    task automatic transfer_edge(
        input logic [5:0] lane_data,
        input logic       frame_value
    );
        begin
            rx_d_p = lane_data;
            rx_frame_p = frame_value;
            #4;
            rx_clk_p = ~rx_clk_p;
            #1;
            check_tx_edge();
            #5;
        end
    endtask

    task automatic transfer_sample(
        input logic [11:0] expected_rx_i,
        input logic [11:0] expected_rx_q,
        input logic        corrupt_frame
    );
        logic [31:0] expected_packed;
        begin
            expected_packed = {expected_rx_i, 4'b0000, expected_rx_q, 4'b0000};

            transfer_edge(expected_rx_i[11:6], 1'b1);
            transfer_edge(expected_rx_q[11:6], 1'b1);
            transfer_edge(expected_rx_i[5:0], corrupt_frame ? 1'b1 : 1'b0);
            transfer_edge(expected_rx_q[5:0], 1'b0);

            if (!rx_sample_valid) begin
                $display("ERROR RX sample_valid missing for sample %0d", sample_index);
                errors = errors + 1;
            end
            if ((rx_i !== expected_rx_i) || (rx_q !== expected_rx_q)) begin
                $display("ERROR RX expected I=%03h Q=%03h got I=%03h Q=%03h",
                    expected_rx_i, expected_rx_q, rx_i, rx_q);
                errors = errors + 1;
            end else begin
                checked_rx_samples = checked_rx_samples + 1;
            end
            if (rx_packed !== expected_packed) begin
                $display("ERROR PACK expected=%08h got=%08h", expected_packed, rx_packed);
                errors = errors + 1;
            end

            $display("SAMPLE %02d RX I=%03h Q=%03h PACK=%08h | TX I=%03h Q=%03h",
                sample_index, rx_i, rx_q, rx_packed, expected_tx_i, expected_tx_q);
        end
    endtask

    initial begin
        // Generate a real reset edge so every behavioral state element is
        // initialized in simulators that do not trigger on an initial value.
        rst = 1'b1;
        inject_frame_error = $test$plusargs("INJECT_FRAME_ERROR");
        if (!$value$plusargs("VCD=%s", vcd_file))
            vcd_file = "ad9361_lvds_1r1t.vcd";

        $dumpfile(vcd_file);
        $dumpvars(0, tb_nyquist_ad9361_lvds_1r1t);

        $display("============================================================");
        $display("NYQUIST SDR AD9361 1R1T DDR LVDS INTERFACE SIMULATION");
        $display("Wire order per complex sample: Ihi, Qhi, Ilo, Qlo");
        $display("Frame pattern: 1, 1, 0, 0");
        $display("Fault injection enabled: %0d", inject_frame_error);
        $display("============================================================");

        #12;
        rst = 1'b0;
        tx_sample_valid = 1'b1;

        for (sample_index = 0; sample_index < 16; sample_index = sample_index + 1) begin
            expected_tx_i = 12'h300 + sample_index;
            expected_tx_q = 12'hC00 + sample_index;
            tx_i = expected_tx_i;
            tx_q = expected_tx_q;

            transfer_sample(
                12'h100 + sample_index,
                12'hE00 + sample_index,
                inject_frame_error && (sample_index == 8)
            );
        end

        if (rx_sample_count !== 16 || tx_sample_count !== 16) begin
            $display("ERROR sample counters RX=%0d TX=%0d", rx_sample_count, tx_sample_count);
            errors = errors + 1;
        end
        if (checked_rx_samples != 16 || checked_tx_samples != 16) begin
            $display("ERROR checker counts RX=%0d TX=%0d", checked_rx_samples, checked_tx_samples);
            errors = errors + 1;
        end
        if (rx_diff_error_count !== 0) begin
            $display("ERROR unexpected differential errors=%0d", rx_diff_error_count);
            errors = errors + 1;
        end

        if (inject_frame_error) begin
            if (rx_frame_error_count !== 1) begin
                $display("ERROR expected exactly one frame error, got %0d", rx_frame_error_count);
                errors = errors + 1;
            end else begin
                $display("FAULT-INJECTION PASS: deliberate frame error detected");
            end
        end else if (rx_frame_error_count !== 0) begin
            $display("ERROR unexpected frame errors=%0d", rx_frame_error_count);
            errors = errors + 1;
        end

        if (errors == 0) begin
            $display("SIM PASS: RX/TX DDR serialization, frame timing, differential complements,");
            $display("          I/Q reconstruction and UHD 32-bit packing all verified.");
        end else begin
            $fatal(1, "SIM FAIL: %0d checks failed", errors);
        end

        #10;
        $finish;
    end

endmodule

Firmware/sim/ad9361_lvds_1r1t/results/frame_error.vcd
$date
	Wed Aug 05 23:52:40 2026
$end
$version
	Icarus Verilog
$end
$timescale
	1ps
$end
$scope module tb_nyquist_ad9361_lvds_1r1t $end
$var wire 1 ! rx_clk_n $end
$var wire 6 " rx_d_n [5:0] $end
$var wire 1 # rx_frame_n $end
$var wire 32 $ tx_sample_count [31:0] $end
$var wire 1 % tx_frame_p $end
$var wire 1 & tx_frame_n $end
$var wire 6 ' tx_d_p [5:0] $end
$var wire 6 ( tx_d_n [5:0] $end
$var wire 1 ) tx_clk_p $end
$var wire 1 * tx_clk_n $end
$var wire 1 + rx_sample_valid $end
$var wire 32 , rx_sample_count [31:0] $end
$var wire 12 - rx_q [11:0] $end
$var wire 32 . rx_packed [31:0] $end
$var wire 12 / rx_i [11:0] $end
$var wire 32 0 rx_frame_error_count [31:0] $end
$var wire 32 1 rx_diff_error_count [31:0] $end
$var reg 12 2 expected_tx_i [11:0] $end
$var reg 12 3 expected_tx_q [11:0] $end
$var reg 1 4 rst $end
$var reg 1 5 rx_clk_p $end
$var reg 6 6 rx_d_p [5:0] $end
$var reg 1 7 rx_frame_p $end
$var reg 12 8 tx_check_i [11:0] $end
$var reg 2 9 tx_check_phase [1:0] $end
$var reg 12 : tx_check_q [11:0] $end
$var reg 12 ; tx_i [11:0] $end
$var reg 12 < tx_q [11:0] $end
$var reg 1 = tx_sample_valid $end
$var reg 2048 > vcd_file [2047:0] $end
$var integer 32 ? checked_rx_samples [31:0] $end
$var integer 32 @ checked_tx_samples [31:0] $end
$var integer 32 A errors [31:0] $end
$var integer 32 B inject_frame_error [31:0] $end
$var integer 32 C sample_index [31:0] $end
$scope module dut $end
$var wire 1 4 rst $end
$var wire 1 ! rx_clk_n $end
$var wire 1 5 rx_clk_p $end
$var wire 6 D rx_d_n [5:0] $end
$var wire 6 E rx_d_p [5:0] $end
$var wire 1 # rx_frame_n $end
$var wire 1 7 rx_frame_p $end
$var wire 1 * tx_clk_n $end
$var wire 1 ) tx_clk_p $end
$var wire 6 F tx_d_n [5:0] $end
$var wire 1 & tx_frame_n $end
$var wire 12 G tx_i [11:0] $end
$var wire 12 H tx_q [11:0] $end
$var wire 1 = tx_sample_valid $end
$var wire 32 I rx_packed [31:0] $end
$var reg 1 J expected_frame $end
$var reg 32 K rx_diff_error_count [31:0] $end
$var reg 32 L rx_frame_error_count [31:0] $end
$var reg 12 M rx_i [11:0] $end
$var reg 12 N rx_i_work [11:0] $end
$var reg 2 O rx_phase [1:0] $end
$var reg 12 P rx_q [11:0] $end
$var reg 12 Q rx_q_work [11:0] $end
$var reg 32 R rx_sample_count [31:0] $end
$var reg 1 + rx_sample_valid $end
$var reg 6 S tx_d_p [5:0] $end
$var reg 1 % tx_frame_p $end
$var reg 12 T tx_i_latched [11:0] $end
$var reg 2 U tx_phase [1:0] $end
$var reg 12 V tx_q_latched [11:0] $end
$var reg 32 W tx_sample_count [31:0] $end
$upscope $end
$scope task check_tx_edge $end
$upscope $end
$scope task transfer_edge $end
$upscope $end
$scope task transfer_sample $end
$upscope $end
$upscope $end
$enddefinitions $end
$comment Show the parameter values. $end
$dumpall
$end
#0
$dumpvars
b0 W
b0 V
b0 U
b0 T
b0 S
b0 R
b0 Q
b0 P
b0 O
b0 N
b0 M
b0 L
b0 K
xJ
b0 I
b0 H
b0 G
b111111 F
b0 E
b111111 D
bx C
b1 B
b0 A
b0 @
b0 ?
b10001100011101001011100010100110100010001010010010111000110111001111001011100010111010101101001011100110111010000101101011100110110010001110010010111000100011001101001011100100110110101110111011000010111001001100101010111000111001101101001011011010101110001100001011001000011100100110011001101100011000101011111011011000111011001100100011100110101111100110001011100100011000101110100010111000111001001100101011100110111010101101100011101000111001101011100011001100111001001100001011011010110010101011111011001010111001001110010011011110111001000101110011101100110001101100100 >
0=
b0 <
b0 ;
b0 :
b0 9
b0 8
07
b0 6
05
14
b0 3
b0 2
b0 1
b0 0
b0 /
b0 .
b0 -
b0 ,
0+
1*
0)
b111111 (
b0 '
1&
0%
b0 $
1#
b111111 "
1!
$end
#12000
0#
b111011 "
b111011 D
17
b100 6
b100 E
b110000000000 <
b110000000000 H
b1100000000 ;
b1100000000 G
b110000000000 3
b1100000000 2
b0 C
1=
04
#16000
b110011 (
b110011 F
0&
b1 U
b1100 '
b1100 S
1%
b110000000000 V
b1100000000 T
b1 O
b100000000 N
1J
0*
0!
1)
15
#17000
b1 9
b1100000000 8
#22000
b111 "
b111 D
b111000 6
b111000 E
#26000
b1111 (
b1111 F
b10 O
b111000000000 Q
b10 U
b110000 '
b110000 S
1*
1!
0)
05
#27000
b10 9
b110000000000 :
#32000
1#
b111111 "
b111111 D
07
b0 6
b0 E
#36000
b111111 (
b111111 F
1&
b11 U
b0 '
b0 S
0%
b11 O
0J
0*
0!
1)
15
#37000
b11 9
#46000
b0 O
b1 ,
b1 R
1+
b111000000000 -
b111000000000 P
b10000000000001110000000000000 .
b10000000000001110000000000000 I
b100000000 /
b100000000 M
b0 U
b1 $
b1 W
1*
1!
0)
05
#47000
b0 9
b1 @
#52000
0#
b111011 "
b111011 D
17
b100 6
b100 E
b110000000001 <
b110000000001 H
b1100000001 ;
b1100000001 G
b110000000001 3
b1100000001 2
b1 C
b1 ?
#56000
b110011 (
b110011 F
0&
b1 U
b1100 '
b1100 S
1%
b110000000001 V
b1100000001 T
b1 O
1J
0+
0*
0!
1)
15
#57000
b1 9
#62000
b111 "
b111 D
b111000 6
b111000 E
#66000
b1111 (
b1111 F
b10 O
b10 U
b110000 '
b110000 S
1*
1!
0)
05
#67000
b10 9
#72000
1#
b111110 "
b111110 D
07
b1 6
b1 E
#76000
b111110 (
b111110 F
1&
b11 U
b1 '
b1 S
0%
b11 O
b100000001 N
0J
0*
0!
1)
15
#77000
b11 9
b1100000001 8
#86000
b0 O
b10 ,
b10 R
1+
b111000000001 -
b111000000001 P
b10000000100001110000000010000 .
b10000000100001110000000010000 I
b100000001 /
b100000001 M
b111000000001 Q
b0 U
b10 $
b10 W
1*
1!
0)
05
#87000
b0 9
b10 @
b110000000001 :
#92000
0#
b111011 "
b111011 D
17
b100 6
b100 E
b110000000010 <
b110000000010 H
b1100000010 ;
b1100000010 G
b110000000010 3
b1100000010 2
b10 C
b10 ?
#96000
b110011 (
b110011 F
0&
b1 U
b1100 '
b1100 S
1%
b110000000010 V
b1100000010 T
b1 O
1J
0+
0*
0!
1)
15
#97000
b1 9
#102000
b111 "
b111 D
b111000 6
b111000 E
#106000
b1111 (
b1111 F
b10 O
b10 U
b110000 '
b110000 S
1*
1!
0)
05
#107000
b10 9
#112000
1#
b111101 "
b111101 D
07
b10 6
b10 E
#116000
b111101 (
b111101 F
1&
b11 U
b10 '
b10 S
0%
b11 O
b100000010 N
0J
0*
0!
1)
15
#117000
b11 9
b1100000010 8
#126000
b0 O
b11 ,
b11 R
1+
b111000000010 -
b111000000010 P
b10000001000001110000000100000 .
b10000001000001110000000100000 I
b100000010 /
b100000010 M
b111000000010 Q
b0 U
b11 $
b11 W
1*
1!
0)
05
#127000
b0 9
b11 @
b110000000010 :
#132000
0#
b111011 "
b111011 D
17
b100 6
b100 E
b110000000011 <
b110000000011 H
b1100000011 ;
b1100000011 G
b110000000011 3
b1100000011 2
b11 C
b11 ?
#136000
b110011 (
b110011 F
0&
b1 U
b1100 '
b1100 S
1%
b110000000011 V
b1100000011 T
b1 O
1J
0+
0*
0!
1)
15
#137000
b1 9
#142000
b111 "
b111 D
b111000 6
b111000 E
#146000
b1111 (
b1111 F
b10 O
b10 U
b110000 '
b110000 S
1*
1!
0)
05
#147000
b10 9
#152000
1#
b111100 "
b111100 D
07
b11 6
b11 E
#156000
b111100 (
b111100 F
1&
b11 U
b11 '
b11 S
0%
b11 O
b100000011 N
0J
0*
0!
1)
15
#157000
b11 9
b1100000011 8
#166000
b0 O
b100 ,
b100 R
1+
b111000000011 -
b111000000011 P
b10000001100001110000000110000 .
b10000001100001110000000110000 I
b100000011 /
b100000011 M
b111000000011 Q
b0 U
b100 $
b100 W
1*
1!
0)
05
#167000
b0 9
b100 @
b110000000011 :
#172000
0#
b111011 "
b111011 D
17
b100 6
b100 E
b110000000100 <
b110000000100 H
b1100000100 ;
b1100000100 G
b110000000100 3
b1100000100 2
b100 C
b100 ?
#176000
b110011 (
b110011 F
0&
b1 U
b1100 '
b1100 S
1%
b110000000100 V
b1100000100 T
b1 O
1J
0+
0*
0!
1)
15
#177000
b1 9
#182000
b111 "
b111 D
b111000 6
b111000 E
#186000
b1111 (
b1111 F
b10 O
b10 U
b110000 '
b110000 S
1*
1!
0)
05
#187000
b10 9
#192000
1#
b111011 "
b111011 D
07
b100 6
b100 E
#196000
b111011 (
b111011 F
1&
b11 U
b100 '
b100 S
0%
b11 O
b100000100 N
0J
0*
0!
1)
15
#197000
b11 9
b1100000100 8
#206000
b0 O
b101 ,
b101 R
1+
b111000000100 -
b111000000100 P
b10000010000001110000001000000 .
b10000010000001110000001000000 I
b100000100 /
b100000100 M
b111000000100 Q
b0 U
b101 $
b101 W
1*
1!
0)
05
#207000
b0 9
b101 @
b110000000100 :
#212000
0#
17
b110000000101 <
b110000000101 H
b1100000101 ;
b1100000101 G
b110000000101 3
b1100000101 2
b101 C
b101 ?
#216000
b110011 (
b110011 F
0&
b1 U
b1100 '
b1100 S
1%
b110000000101 V
b1100000101 T
b1 O
1J
0+
0*
0!
1)
15
#217000
b1 9
#222000
b111 "
b111 D
b111000 6
b111000 E
#226000
b1111 (
b1111 F
b10 O
b10 U
b110000 '
b110000 S
1*
1!
0)
05
#227000
b10 9
#232000
1#
b111010 "
b111010 D
07
b101 6
b101 E
#236000
b111010 (
b111010 F
1&
b11 U
b101 '
b101 S
0%
b11 O
b100000101 N
0J
0*
0!
1)
15
#237000
b11 9
b1100000101 8
#246000
b0 O
b110 ,
b110 R
1+
b111000000101 -
b111000000101 P
b10000010100001110000001010000 .
b10000010100001110000001010000 I
b100000101 /
b100000101 M
b111000000101 Q
b0 U
b110 $
b110 W
1*
1!
0)
05
#247000
b0 9
b110 @
b110000000101 :
#252000
0#
b111011 "
b111011 D
17
b100 6
b100 E
b110000000110 <
b110000000110 H
b1100000110 ;
b1100000110 G
b110000000110 3
b1100000110 2
b110 C
b110 ?
#256000
b110011 (
b110011 F
0&
b1 U
b1100 '
b1100 S
1%
b110000000110 V
b1100000110 T
b1 O
1J
0+
0*
0!
1)
15
#257000
b1 9
#262000
b111 "
b111 D
b111000 6
b111000 E
#266000
b1111 (
b1111 F
b10 O
b10 U
b110000 '
b110000 S
1*
1!
0)
05
#267000
b10 9
#272000
1#
b111001 "
b111001 D
07
b110 6
b110 E
#276000
b111001 (
b111001 F
1&
b11 U
b110 '
b110 S
0%
b11 O
b100000110 N
0J
0*
0!
1)
15
#277000
b11 9
b1100000110 8
#286000
b0 O
b111 ,
b111 R
1+
b111000000110 -
b111000000110 P
b10000011000001110000001100000 .
b10000011000001110000001100000 I
b100000110 /
b100000110 M
b111000000110 Q
b0 U
b111 $
b111 W
1*
1!
0)
05
#287000
b0 9
b111 @
b110000000110 :
#292000
0#
b111011 "
b111011 D
17
b100 6
b100 E
b110000000111 <
b110000000111 H
b1100000111 ;
b1100000111 G
b110000000111 3
b1100000111 2
b111 C
b111 ?
#296000
b110011 (
b110011 F
0&
b1 U
b1100 '
b1100 S
1%
b110000000111 V
b1100000111 T
b1 O
1J
0+
0*
0!
1)
15
#297000
b1 9
#302000
b111 "
b111 D
b111000 6
b111000 E
#306000
b1111 (
b1111 F
b10 O
b10 U
b110000 '
b110000 S
1*
1!
0)
05
#307000
b10 9
#312000
1#
b111000 "
b111000 D
07
b111 6
b111 E
#316000
b111000 (
b111000 F
1&
b11 U
b111 '
b111 S
0%
b11 O
b100000111 N
0J
0*
0!
1)
15
#317000
b11 9
b1100000111 8
#326000
b0 O
b1000 ,
b1000 R
1+
b111000000111 -
b111000000111 P
b10000011100001110000001110000 .
b10000011100001110000001110000 I
b100000111 /
b100000111 M
b111000000111 Q
b0 U
b1000 $
b1000 W
1*
1!
0)
05
#327000
b0 9
b1000 @
b110000000111 :
#332000
0#
b111011 "
b111011 D
17
b100 6
b100 E
b110000001000 <
b110000001000 H
b1100001000 ;
b1100001000 G
b110000001000 3
b1100001000 2
b1000 C
b1000 ?
#336000
b110011 (
b110011 F
0&
b1 U
b1100 '
b1100 S
1%
b110000001000 V
b1100001000 T
b1 O
1J
0+
0*
0!
1)
15
#337000
b1 9
#342000
b111 "
b111 D
b111000 6
b111000 E
#346000
b1111 (
b1111 F
b10 O
b10 U
b110000 '
b110000 S
1*
1!
0)
05
#347000
b10 9
#352000
b110111 "
b110111 D
b1000 6
b1000 E
#356000
b110111 (
b110111 F
1&
b11 U
b1000 '
b1000 S
0%
b11 O
b100001000 N
b1 0
b1 L
0J
0*
0!
1)
15
#357000
b11 9
b1100001000 8
#362000
1#
07
#366000
b0 O
b1001 ,
b1001 R
1+
b111000001000 -
b111000001000 P
b10000100000001110000010000000 .
b10000100000001110000010000000 I
b100001000 /
b100001000 M
b111000001000 Q
b0 U
b1001 $
b1001 W
1*
1!
0)
05
#367000
b0 9
b1001 @
b110000001000 :
#372000
0#
b111011 "
b111011 D
17
b100 6
b100 E
b110000001001 <
b110000001001 H
b1100001001 ;
b1100001001 G
b110000001001 3
b1100001001 2
b1001 C
b1001 ?
#376000
b110011 (
b110011 F
0&
b1 U
b1100 '
b1100 S
1%
b110000001001 V
b1100001001 T
b1 O
1J
0+
0*
0!
1)
15
#377000
b1 9
#382000
b111 "
b111 D
b111000 6
b111000 E
#386000
b1111 (
b1111 F
b10 O
b10 U
b110000 '
b110000 S
1*
1!
0)
05
#387000
b10 9
#392000
1#
b110110 "
b110110 D
07
b1001 6
b1001 E
#396000
b110110 (
b110110 F
1&
b11 U
b1001 '
b1001 S
0%
b11 O
b100001001 N
0J
0*
0!
1)
15
#397000
b11 9
b1100001001 8
#406000
b0 O
b1010 ,
b1010 R
1+
b111000001001 -
b111000001001 P
b10000100100001110000010010000 .
b10000100100001110000010010000 I
b100001001 /
b100001001 M
b111000001001 Q
b0 U
b1010 $
b1010 W
1*
1!
0)
05
#407000
b0 9
b1010 @
b110000001001 :
#412000
0#
b111011 "
b111011 D
17
b100 6
b100 E
b110000001010 <
b110000001010 H
b1100001010 ;
b1100001010 G
b110000001010 3
b1100001010 2
b1010 C
b1010 ?
#416000
b110011 (
b110011 F
0&
b1 U
b1100 '
b1100 S
1%
b110000001010 V
b1100001010 T
b1 O
1J
0+
0*
0!
1)
15
#417000
b1 9
#422000
b111 "
b111 D
b111000 6
b111000 E
#426000
b1111 (
b1111 F
b10 O
b10 U
b110000 '
b110000 S
1*
1!
0)
05
#427000
b10 9
#432000
1#
b110101 "
b110101 D
07
b1010 6
b1010 E
#436000
b110101 (
b110101 F
1&
b11 U
b1010 '
b1010 S
0%
b11 O
b100001010 N
0J
0*
0!
1)
15
#437000
b11 9
b1100001010 8
#446000
b0 O
b1011 ,
b1011 R
1+
b111000001010 -
b111000001010 P
b10000101000001110000010100000 .
b10000101000001110000010100000 I
b100001010 /
b100001010 M
b111000001010 Q
b0 U
b1011 $
b1011 W
1*
1!
0)
05
#447000
b0 9
b1011 @
b110000001010 :
#452000
0#
b111011 "
b111011 D
17
b100 6
b100 E
b110000001011 <
b110000001011 H
b1100001011 ;
b1100001011 G
b110000001011 3
b1100001011 2
b1011 C
b1011 ?
#456000
b110011 (
b110011 F
0&
b1 U
b1100 '
b1100 S
1%
b110000001011 V
b1100001011 T
b1 O
1J
0+
0*
0!
1)
15
#457000
b1 9
#462000
b111 "
b111 D
b111000 6
b111000 E
#466000
b1111 (
b1111 F
b10 O
b10 U
b110000 '
b110000 S
1*
1!
0)
05
#467000
b10 9
#472000
1#
b110100 "
b110100 D
07
b1011 6
b1011 E
#476000
b110100 (
b110100 F
1&
b11 U
b1011 '
b1011 S
0%
b11 O
b100001011 N
0J
0*
0!
1)
15
#477000
b11 9
b1100001011 8
#486000
b0 O
b1100 ,
b1100 R
1+
b111000001011 -
b111000001011 P
b10000101100001110000010110000 .
b10000101100001110000010110000 I
b100001011 /
b100001011 M
b111000001011 Q
b0 U
b1100 $
b1100 W
1*
1!
0)
05
#487000
b0 9
b1100 @
b110000001011 :
#492000
0#
b111011 "
b111011 D
17
b100 6
b100 E
b110000001100 <
b110000001100 H
b1100001100 ;
b1100001100 G
b110000001100 3
b1100001100 2
b1100 C
b1100 ?
#496000
b110011 (
b110011 F
0&
b1 U
b1100 '
b1100 S
1%
b110000001100 V
b1100001100 T
b1 O
1J
0+
0*
0!
1)
15
#497000
b1 9
#502000
b111 "
b111 D
b111000 6
b111000 E
#506000
b1111 (
b1111 F
b10 O
b10 U
b110000 '
b110000 S
1*
1!
0)
05
#507000
b10 9
#512000
1#
b110011 "
b110011 D
07
b1100 6
b1100 E
#516000
b110011 (
b110011 F
1&
b11 U
b1100 '
b1100 S
0%
b11 O
b100001100 N
0J
0*
0!
1)
15
#517000
b11 9
b1100001100 8
#526000
b0 O
b1101 ,
b1101 R
1+
b111000001100 -
b111000001100 P
b10000110000001110000011000000 .
b10000110000001110000011000000 I
b100001100 /
b100001100 M
b111000001100 Q
b0 U
b1101 $
b1101 W
1*
1!
0)
05
#527000
b0 9
b1101 @
b110000001100 :
#532000
0#
b111011 "
b111011 D
17
b100 6
b100 E
b110000001101 <
b110000001101 H
b1100001101 ;
b1100001101 G
b110000001101 3
b1100001101 2
b1101 C
b1101 ?
#536000
0&
b1 U
1%
b110000001101 V
b1100001101 T
b1 O
1J
0+
0*
0!
1)
15
#537000
b1 9
#542000
b111 "
b111 D
b111000 6
b111000 E
#546000
b1111 (
b1111 F
b10 O
b10 U
b110000 '
b110000 S
1*
1!
0)
05
#547000
b10 9
#552000
1#
b110010 "
b110010 D
07
b1101 6
b1101 E
#556000
b110010 (
b110010 F
1&
b11 U
b1101 '
b1101 S
0%
b11 O
b100001101 N
0J
0*
0!
1)
15
#557000
b11 9
b1100001101 8
